minos/plugins/kafka/__init__.py
minos/plugins/kafka/common.py
minos/plugins/kafka/publisher.py
minos/plugins/kafka/subscriber.py
minos_broker_kafka-0.7.0.dist-info/LICENSE
minos_broker_kafka-0.7.0.dist-info/WHEEL
minos_broker_kafka-0.7.0.dist-info/METADATA
minos_broker_kafka-0.7.0.dist-info/RECORD
